restq_py/__init__.py
restq_py/clients.py
restq_py/decorator.py
restq_py/exceptions.py
restq_py/logger.py
restq_py/queue.py
restq_py/task.py
restq_py/types.py
restq_py/worker.py
restq_py-0.1.0.dist-info/METADATA
restq_py-0.1.0.dist-info/WHEEL
restq_py-0.1.0.dist-info/RECORD
