Metadata-Version: 2.1
Name: restq-py
Version: 0.1.0
Summary: Restq is a lightweight high-performance task queue built on top of Redis
Home-page: https://github.com/dakohhh/restq
License: MIT
Keywords: queue,task,worker,lightweight
Author: dakohhh
Author-email: wiizzydreadmill@gmail.com
Requires-Python: >=3.9,<4.0
Classifier: License :: OSI Approved :: MIT License
Classifier: Programming Language :: Python :: 3
Classifier: Programming Language :: Python :: 3.9
Classifier: Programming Language :: Python :: 3.10
Classifier: Programming Language :: Python :: 3.11
Classifier: Programming Language :: Python :: 3.12
Requires-Dist: anyio (>=4.10.0,<5.0.0)
Requires-Dist: colorama (>=0.4.6,<0.5.0)
Requires-Dist: orjson (>=3.11.1,<4.0.0)
Requires-Dist: pydantic (>=2.11.7,<3.0.0)
Requires-Dist: redis (==5.3.1)
Project-URL: Repository, https://github.com/dakohhh/restq
